{
  "users": [
    { "id": "123", "name": "Paolo", "age": 25, "dateOfBirth": "1995-01-01" },
    { "id": "456", "name": "John", "age": 30, "dateOfBirth": "1990-01-01" },
    { "id": "789", "name": "Jane", "age": 35, "dateOfBirth": "1985-01-01" },
    {
      "id": "124",
      "name": "Pal",
      "age": 22,
      "dateOfBirth": "2011-12-28 23:55:59.342380"
    },
    {
      "id": "457",
      "name": "Joh",
      "age": 33,
      "dateOfBirth": "2011-12-28 23:55:59.342380"
    },
    {
      "id": "790",
      "name": "Jan",
      "age": 38,
      "dateOfBirth": "2011-08-12T20:17:46.384Z"
    }
  ]
}
